Metadata-Version: 2.1
Name: Distribution-1-3
Version: 0.2
Summary: Probability Distributions
Author: Tomi_Abdul
Author-email: amusatomisin65@gmail.com
License: UNKNOWN
Platform: UNKNOWN
License-File: license.txt
